[
  {
    "Type": "ArtDataArmor",
    "Name": "CopperlightAttire_3001",
    "Class": "UScriptClass'ArtDataArmor'",
    "Properties": {
      "MorphTargetsV2": [
        {
          "Key": "EDCMorphTarget::LizardmanNeck",
          "Value": 1.0
        },
        {
          "Key": "EDCMorphTarget::Hood",
          "Value": 1.0
        }
      ],
      "ItemIconTexture": {
        "ObjectName": "Texture2D'Item_Icon_CopperlightAttire'",
        "ObjectPath": "DungeonCrawler/Content/DungeonCrawler/Item/Armor/Chest/CopperlightAttire/Icon/Item_Icon_CopperlightAttire.0"
      },
      "ItemSkeletalMesh": {
        "ObjectName": "SkeletalMesh'SK_CopperlightAttire'",
        "ObjectPath": "DungeonCrawler/Content/DungeonCrawler/Item/Armor/Chest/CopperlightAttire/SK_CopperlightAttire.1"
      },
      "ItemStaticMesh": {
        "ObjectName": "StaticMesh'SM_CopperlightAttire_Holder'",
        "ObjectPath": "DungeonCrawler/Content/DungeonCrawler/Item/Armor/Chest/CopperlightAttire/SM_CopperlightAttire_Holder.2"
      }
    }
  }
]