[
  {
    "Type": "MaterialInstanceConstant",
    "Name": "MI_Aegis_Flare",
    "Class": "UScriptClass'MaterialInstanceConstant'",
    "Properties": {
      "Parent": {
        "ObjectName": "Material'M_Flare_Dynamic'",
        "ObjectPath": "DungeonCrawler/Content/DungeonCrawler/FX/Shared_Resource/Materials/M_Flare_Dynamic.0"
      },
      "bHasStaticPermutationResource": true,
      "ScalarParameterValues": [
        {
          "ParameterInfo": {
            "Name": "Center Offset",
            "Association": "EMaterialParameterAssociation::GlobalParameter",
            "Index": -1
          },
          "ParameterValue": -0.05974,
          "ExpressionGUID": "5207B159-47B9B7D5-303E308A-710D4250"
        },
        {
          "ParameterInfo": {
            "Name": "Contrast",
            "Association": "EMaterialParameterAssociation::GlobalParameter",
            "Index": -1
          },
          "ParameterValue": 0.997096,
          "ExpressionGUID": "2C6A0532-4A0AE80C-0B0600A3-F549A1F3"
        },
        {
          "ParameterInfo": {
            "Name": "Core Addition Multiplier",
            "Association": "EMaterialParameterAssociation::GlobalParameter",
            "Index": -1
          },
          "ParameterValue": 0.304,
          "ExpressionGUID": "DC6C725F-460BC709-B7EF4BBC-37B5079E"
        },
        {
          "ParameterInfo": {
            "Name": "Core Density",
            "Association": "EMaterialParameterAssociation::GlobalParameter",
            "Index": -1
          },
          "ParameterValue": 0.993716,
          "ExpressionGUID": "E9D71E28-4E5E8200-97DF5084-E8633C81"
        },
        {
          "ParameterInfo": {
            "Name": "Core Radius",
            "Association": "EMaterialParameterAssociation::GlobalParameter",
            "Index": -1
          },
          "ParameterValue": 0.384,
          "ExpressionGUID": "0773370A-47329113-FC3A86BE-F7BFCC48"
        },
        {
          "ParameterInfo": {
            "Name": "Param_7",
            "Association": "EMaterialParameterAssociation::GlobalParameter",
            "Index": -1
          },
          "ParameterValue": 2.332478,
          "ExpressionGUID": "CA30C042-491D58D0-6ED2A78A-E744D21E"
        },
        {
          "ParameterInfo": {
            "Name": "Texture Scale",
            "Association": "EMaterialParameterAssociation::GlobalParameter",
            "Index": -1
          },
          "ParameterValue": 1.0,
          "ExpressionGUID": "DFEA77BE-42988D8D-FDF71982-0898AAF6"
        },
        {
          "ParameterInfo": {
            "Name": "Texture Scale U",
            "Association": "EMaterialParameterAssociation::GlobalParameter",
            "Index": -1
          },
          "ParameterValue": 1.0,
          "ExpressionGUID": "46DD40E6-4D775D2C-76D3539C-52268418"
        },
        {
          "ParameterInfo": {
            "Name": "U Scroll",
            "Association": "EMaterialParameterAssociation::GlobalParameter",
            "Index": -1
          },
          "ParameterValue": -0.05,
          "ExpressionGUID": "B5EC49DF-481C8E81-137B88A9-FE360B41"
        },
        {
          "ParameterInfo": {
            "Name": "V Scroll",
            "Association": "EMaterialParameterAssociation::GlobalParameter",
            "Index": -1
          },
          "ParameterValue": 0.01,
          "ExpressionGUID": "55B90390-4D1FDDDA-65A01EA6-A21A96A9"
        },
        {
          "ParameterInfo": {
            "Name": "RefractionDepthBias",
            "Association": "EMaterialParameterAssociation::GlobalParameter",
            "Index": -1
          },
          "ParameterValue": 0.0,
          "ExpressionGUID": "00000000-00000000-00000000-00000000"
        }
      ],
      "VectorParameterValues": [
        {
          "ParameterInfo": {
            "Name": "Param",
            "Association": "EMaterialParameterAssociation::GlobalParameter",
            "Index": -1
          },
          "ParameterValue": {
            "R": 0.916375,
            "G": 0.916018,
            "B": 1.0,
            "A": 0.0,
            "Hex": "F6F6FF"
          },
          "ExpressionGUID": "885C6CF2-456F479B-D52A4295-2299A1EF"
        },
        {
          "ParameterInfo": {
            "Name": "Param_1",
            "Association": "EMaterialParameterAssociation::GlobalParameter",
            "Index": -1
          },
          "ParameterValue": {
            "R": 0.924884,
            "G": 1.0,
            "B": 0.929504,
            "A": 0.0,
            "Hex": "F7FFF7"
          },
          "ExpressionGUID": "5E1FD8BC-43CD1AB2-EB20CDA9-D7927ADF"
        }
      ],
      "BasePropertyOverrides": {
        "TwoSided": true,
        "BlendMode": "EBlendMode::BLEND_Additive",
        "ShadingModel": "EMaterialShadingModel::MSM_Unlit",
        "OpacityMaskClipValue": 0.3333
      },
      "StaticParametersRuntime": {
        "StaticSwitchParameters": [
          {
            "Value": true,
            "ParameterInfo": {
              "Name": "Use (+Camera) Depthfade",
              "Association": "EMaterialParameterAssociation::GlobalParameter",
              "Index": -1
            },
            "bOverride": true,
            "ExpressionGUID": "1F62CEAD-496626E4-B196F1B2-931B3EA4"
          }
        ]
      },
      "bIncludedInBaseGame": true
    },
    "CachedData": {
      "ParentLayerIndexRemap": []
    }
  }
]