[
  {
    "Type": "DesignDataAssetItem",
    "Name": "Id_Item_TongueOfMimic",
    "Class": "UScriptClass'DesignDataAssetItem'",
    "Properties": {
      "Item": {
        "IdTag": {
          "TagName": "Id.Item.TongueOfMimic"
        },
        "OriginId": {
          "PrimaryAssetType": {
            "Name": "DesignDataItem"
          },
          "PrimaryAssetName": "Id_Item_TongueOfMimic"
        },
        "Name": {
          "Namespace": "DC",
          "Key": "Text_DesignData_Item_Item_TongueOfMimic",
          "SourceString": "Text_DesignData_Item_Item_TongueOfMimic",
          "LocalizedString": "Mimic Tongue"
        },
        "FlavorText": {
          "Namespace": "DC",
          "Key": "Text_DesignData_Item_Flavor_TongueOfMimic",
          "SourceString": "Text_DesignData_Item_Flavor_TongueOfMimic",
          "LocalizedString": "A grotesque and slimy elongated tongue, taken from the maw of a mimic."
        },
        "ItemType": "EItemType::Misc",
        "MiscType": {
          "TagName": "Type.Item.Misc.HuntingLoot"
        },
        "RarityType": {
          "TagName": "Type.Item.Rarity.Uncommon"
        },
        "MaxCount": 1,
        "CanDrop": true,
        "CanSaveIntoDatabase": true,
        "ArtData": {
          "PrimaryAssetType": {
            "Name": "ArtDataItem"
          },
          "PrimaryAssetName": "TongueOfMimic"
        },
        "SoundData": {
          "PrimaryAssetType": {
            "Name": "SoundData"
          },
          "PrimaryAssetName": "TongueOfMimic_Sound"
        },
        "ItemHolderActorClass": {
          "ObjectName": "BlueprintGeneratedClass'BP_StaticMeshItemHolder_C'",
          "ObjectPath": "DungeonCrawler/Content/DungeonCrawler/Core/Item/BP_StaticMeshItemHolder.1"
        },
        "InventoryWidth": 2,
        "InventoryHeight": 2,
        "AdvPoint": 2,
        "ExpPoint": 1
      }
    }
  }
]