[
  {
    "Type": "DesignDataAssetItem",
    "Name": "Id_Item_HeavyLeatherLeggings_3001",
    "Class": "UScriptClass'DesignDataAssetItem'",
    "Properties": {
      "Item": {
        "IdTag": {
          "TagName": "Id.Item.HeavyLeatherLeggings"
        },
        "OriginId": {
          "PrimaryAssetType": {
            "Name": "DesignDataItem"
          },
          "PrimaryAssetName": "Id_Item_HeavyLeatherLeggings_1001"
        },
        "Name": {
          "Namespace": "DC",
          "Key": "Text_DesignData_Item_Item_HeavyLeatherLeggings_3001",
          "SourceString": "Text_DesignData_Item_Item_HeavyLeatherLeggings_3001",
          "LocalizedString": "Heavy Leather Leggings"
        },
        "FlavorText": {
          "Namespace": "DC",
          "Key": "Text_DesignData_Item_Flavor_HeavyLeatherLeggings_0001",
          "SourceString": "Text_DesignData_Item_Flavor_HeavyLeatherLeggings_0001",
          "LocalizedString": "Made using a much thicker, heavier leather. Added protection over the knees."
        },
        "ItemType": "EItemType::Armor",
        "SlotType": {
          "TagName": "Type.Item.Slot.Legs"
        },
        "ArmorType": {
          "TagName": "Type.Item.Armor.Leather"
        },
        "RarityType": {
          "TagName": "Type.Item.Rarity.Uncommon"
        },
        "MaxCount": 1,
        "CanDrop": true,
        "CanSaveIntoDatabase": true,
        "ArtData": {
          "PrimaryAssetType": {
            "Name": "ArtDataItem"
          },
          "PrimaryAssetName": "HeavyLeatherLeggings_3001"
        },
        "SoundData": {
          "PrimaryAssetType": {
            "Name": "SoundData"
          },
          "PrimaryAssetName": "HeavyLeatherLeggings_Sound"
        },
        "ItemHolderActorClass": {
          "ObjectName": "BlueprintGeneratedClass'BP_StaticMeshItemHolder_C'",
          "ObjectPath": "DungeonCrawler/Content/DungeonCrawler/Core/Item/BP_StaticMeshItemHolder.1"
        },
        "InventoryWidth": 2,
        "InventoryHeight": 3,
        "WearingDelayTime": 1.25,
        "PrimaryProperty": {
          "PrimaryAssetType": {
            "Name": "DesignDataItemProperty"
          },
          "PrimaryAssetName": "Id_ItemProperty_Primary_HeavyLeatherLeggings_3001"
        },
        "SecondaryProperties": [
          {
            "PrimaryAssetType": {
              "Name": "DesignDataItemProperty"
            },
            "PrimaryAssetName": "Id_ItemProperty_Secondary_Legs"
          }
        ],
        "Requirement": {
          "PrimaryAssetType": {
            "Name": "DesignDataItemRequirement"
          },
          "PrimaryAssetName": "Id_ItemRequirement_HeavyLeatherLeggings_3001"
        },
        "AdvPoint": 3,
        "ExpPoint": 3,
        "GearScore": 15
      }
    }
  }
]