[
  {
    "Type": "DesignDataAssetItem",
    "Name": "Id_Item_BlueEyeballs",
    "Class": "UScriptClass'DesignDataAssetItem'",
    "Properties": {
      "Item": {
        "IdTag": {
          "TagName": "Id.Item.BlueEyeballs"
        },
        "OriginId": {
          "PrimaryAssetType": {
            "Name": "DesignDataItem"
          },
          "PrimaryAssetName": "Id_Item_BlueEyeballs"
        },
        "Name": {
          "Namespace": "DC",
          "Key": "Text_DesignData_Item_Item_BlueEyeballs",
          "SourceString": "Text_DesignData_Item_Item_BlueEyeballs",
          "LocalizedString": "Blue Eyeballs"
        },
        "FlavorText": {
          "Namespace": "DC",
          "Key": "Text_DesignData_Item_Flavor_BlueEyeballs",
          "SourceString": "Text_DesignData_Item_Flavor_BlueEyeballs",
          "LocalizedString": "Enigmatic blue eyeballs plucked from the remnants of a Dire Wolf."
        },
        "ItemType": "EItemType::Misc",
        "MiscType": {
          "TagName": "Type.Item.Misc.HuntingLoot"
        },
        "RarityType": {
          "TagName": "Type.Item.Rarity.Rare"
        },
        "MaxCount": 3,
        "CanDrop": true,
        "CanSaveIntoDatabase": true,
        "ArtData": {
          "PrimaryAssetType": {
            "Name": "ArtDataItem"
          },
          "PrimaryAssetName": "BlueEyeballs"
        },
        "SoundData": {
          "PrimaryAssetType": {
            "Name": "SoundData"
          },
          "PrimaryAssetName": "BlueEyeballs_Sound"
        },
        "ItemHolderActorClass": {
          "ObjectName": "BlueprintGeneratedClass'BP_StaticMeshItemHolder_C'",
          "ObjectPath": "DungeonCrawler/Content/DungeonCrawler/Core/Item/BP_StaticMeshItemHolder.1"
        },
        "InventoryWidth": 1,
        "InventoryHeight": 1,
        "AdvPoint": 1,
        "ExpPoint": 1
      }
    }
  }
]