[
  {
    "Type": "DesignDataAssetItem",
    "Name": "Id_Item_FrostlightPlatePants_6001",
    "Class": "UScriptClass'DesignDataAssetItem'",
    "Properties": {
      "Item": {
        "IdTag": {
          "TagName": "Id.Item.FrostlightPlatePants"
        },
        "OriginId": {
          "PrimaryAssetType": {
            "Name": "DesignDataItem"
          },
          "PrimaryAssetName": "Id_Item_FrostlightPlatePants_6001"
        },
        "Name": {
          "Namespace": "DC",
          "Key": "Text_DesignData_Item_Item_FrostlightPlatePants_6001",
          "SourceString": "Text_DesignData_Item_Item_FrostlightPlatePants_6001",
          "LocalizedString": "Frostlight Plate Pants"
        },
        "FlavorText": {
          "Namespace": "DC",
          "Key": "Text_DesignData_Item_Flavor_FrostlightPlatePants_6001",
          "SourceString": "Text_DesignData_Item_Flavor_FrostlightPlatePants_6001",
          "LocalizedString": "Sturdy plate pants forged from froststone ore, integrating the icy resilience of the frozen abyss into every plate and rivet."
        },
        "ItemType": "EItemType::Armor",
        "SlotType": {
          "TagName": "Type.Item.Slot.Legs"
        },
        "ArmorType": {
          "TagName": "Type.Item.Armor.Plate"
        },
        "RarityType": {
          "TagName": "Type.Item.Rarity.Legend"
        },
        "MaxCount": 1,
        "CanDrop": true,
        "CanSaveIntoDatabase": true,
        "ArtData": {
          "PrimaryAssetType": {
            "Name": "ArtDataItem"
          },
          "PrimaryAssetName": "FrostlightPlatePants_6001"
        },
        "SoundData": {
          "PrimaryAssetType": {
            "Name": "SoundData"
          },
          "PrimaryAssetName": "PlatePants_Sound"
        },
        "ItemHolderActorClass": {
          "ObjectName": "BlueprintGeneratedClass'BP_StaticMeshItemHolder_C'",
          "ObjectPath": "DungeonCrawler/Content/DungeonCrawler/Core/Item/BP_StaticMeshItemHolder.1"
        },
        "InventoryWidth": 2,
        "InventoryHeight": 3,
        "WearingDelayTime": 1.75,
        "PrimaryProperty": {
          "PrimaryAssetType": {
            "Name": "DesignDataItemProperty"
          },
          "PrimaryAssetName": "Id_ItemProperty_Primary_FrostlightPlatePants_6001"
        },
        "SecondaryProperties": [
          {
            "PrimaryAssetType": {
              "Name": "DesignDataItemProperty"
            },
            "PrimaryAssetName": "Id_ItemProperty_Secondary_Legs"
          },
          {
            "PrimaryAssetType": {
              "Name": "DesignDataItemProperty"
            },
            "PrimaryAssetName": "Id_ItemProperty_Secondary_Legs"
          },
          {
            "PrimaryAssetType": {
              "Name": "DesignDataItemProperty"
            },
            "PrimaryAssetName": "Id_ItemProperty_Secondary_Legs"
          },
          {
            "PrimaryAssetType": {
              "Name": "DesignDataItemProperty"
            },
            "PrimaryAssetName": "Id_ItemProperty_Secondary_Legs"
          },
          {
            "PrimaryAssetType": {
              "Name": "DesignDataItemProperty"
            },
            "PrimaryAssetName": "Id_ItemProperty_Secondary_Legs"
          }
        ],
        "Requirement": {
          "PrimaryAssetType": {
            "Name": "DesignDataItemRequirement"
          },
          "PrimaryAssetName": "Id_ItemRequirement_FrostlightPlatePants_6001"
        },
        "AdvPoint": 15,
        "ExpPoint": 6,
        "GearScore": 40
      }
    }
  }
]