[
  {
    "Type": "DesignDataAssetItem",
    "Name": "Id_Item_FangsofDeathNecklace_5001",
    "Class": "UScriptClass'DesignDataAssetItem'",
    "Properties": {
      "Item": {
        "IdTag": {
          "TagName": "Id.Item.FangsofDeathNecklace"
        },
        "OriginId": {
          "PrimaryAssetType": {
            "Name": "DesignDataItem"
          },
          "PrimaryAssetName": "Id_Item_FangsofDeathNecklace_5001"
        },
        "Name": {
          "Namespace": "DC",
          "Key": "Text_DesignData_Item_Item_FangsofDeathNecklace_5001",
          "SourceString": "Text_DesignData_Item_Item_FangsofDeathNecklace_5001",
          "LocalizedString": "Fangs of Death Necklace"
        },
        "FlavorText": {
          "Namespace": "DC",
          "Key": "Text_DesignData_Item_Flavor_FangsofDeathNecklace_5001",
          "SourceString": "Text_DesignData_Item_Flavor_FangsofDeathNecklace_5001",
          "LocalizedString": "Necklace crafted using a unique combination of teeth acquired from different beasts."
        },
        "ItemType": "EItemType::Accessory",
        "SlotType": {
          "TagName": "Type.Item.Slot.Necklace"
        },
        "AccessoryType": {
          "TagName": "Type.Item.Accessory.Necklace"
        },
        "RarityType": {
          "TagName": "Type.Item.Rarity.Epic"
        },
        "MaxCount": 1,
        "CanDrop": true,
        "CanSaveIntoDatabase": true,
        "ArtData": {
          "PrimaryAssetType": {
            "Name": "ArtDataItem"
          },
          "PrimaryAssetName": "FangsofDeathNecklace"
        },
        "SoundData": {
          "PrimaryAssetType": {
            "Name": "SoundData"
          },
          "PrimaryAssetName": "SoulTorq_Sound"
        },
        "ItemHolderActorClass": {
          "ObjectName": "BlueprintGeneratedClass'BP_StaticMeshItemHolder_C'",
          "ObjectPath": "DungeonCrawler/Content/DungeonCrawler/Core/Item/BP_StaticMeshItemHolder.1"
        },
        "InventoryWidth": 1,
        "InventoryHeight": 1,
        "PrimaryProperty": {
          "PrimaryAssetType": {
            "Name": "DesignDataItemProperty"
          },
          "PrimaryAssetName": "Id_ItemProperty_Primary_FangsofDeathNecklace_5001"
        },
        "SecondaryProperties": [
          {
            "PrimaryAssetType": {
              "Name": "DesignDataItemProperty"
            },
            "PrimaryAssetName": "Id_ItemProperty_Secondary_Necklace"
          },
          {
            "PrimaryAssetType": {
              "Name": "DesignDataItemProperty"
            },
            "PrimaryAssetName": "Id_ItemProperty_Secondary_Necklace"
          },
          {
            "PrimaryAssetType": {
              "Name": "DesignDataItemProperty"
            },
            "PrimaryAssetName": "Id_ItemProperty_Secondary_Necklace"
          },
          {
            "PrimaryAssetType": {
              "Name": "DesignDataItemProperty"
            },
            "PrimaryAssetName": "Id_ItemProperty_Secondary_Necklace"
          }
        ],
        "Requirement": {
          "PrimaryAssetType": {
            "Name": "DesignDataItemRequirement"
          },
          "PrimaryAssetName": "Id_ItemRequirement_FangsofDeathNecklace_5001"
        },
        "AdvPoint": 2,
        "ExpPoint": 4,
        "GearScore": 18
      }
    }
  }
]